sparkdv/__init__.py
sparkdv-0.1.0.dist-info/METADATA
sparkdv-0.1.0.dist-info/WHEEL
sparkdv-0.1.0.dist-info/top_level.txt
sparkdv-0.1.0.dist-info/RECORD
